pinboard_tools/__init__.py
pinboard_tools/py.typed
pinboard_tools/analysis/__init__.py
pinboard_tools/analysis/consolidation.py
pinboard_tools/analysis/similarity.py
pinboard_tools/data/__init__.py
pinboard_tools/data/schema.sql
pinboard_tools/database/__init__.py
pinboard_tools/database/migrations.py
pinboard_tools/database/models.py
pinboard_tools/database/queries.py
pinboard_tools/sync/__init__.py
pinboard_tools/sync/api.py
pinboard_tools/sync/bidirectional.py
pinboard_tools/utils/__init__.py
pinboard_tools/utils/chunking.py
pinboard_tools/utils/datetime.py
pinboard_tools/utils/display.py
pinboard_tools-0.1.9.dist-info/METADATA
pinboard_tools-0.1.9.dist-info/WHEEL
pinboard_tools-0.1.9.dist-info/licenses/LICENSE
pinboard_tools-0.1.9.dist-info/RECORD
