Metadata-Version: 2.4
Name: pinboard-tools
Version: 0.1.9
Summary: A Python library for syncing and managing Pinboard bookmarks
Author-email: Kevin McMahon <87225+kevinmcmahon@users.noreply.github.com>
License: Apache-2.0
License-File: LICENSE
Keywords: api,bookmarks,pinboard,sync
Classifier: Development Status :: 4 - Beta
Classifier: Intended Audience :: Developers
Classifier: License :: OSI Approved :: Apache Software License
Classifier: Programming Language :: Python :: 3
Classifier: Programming Language :: Python :: 3.11
Classifier: Programming Language :: Python :: 3.12
Classifier: Programming Language :: Python :: 3.13
Classifier: Topic :: Internet :: WWW/HTTP
Classifier: Topic :: Software Development :: Libraries :: Python Modules
Requires-Python: >=3.11
Requires-Dist: requests>=2.31.0
Requires-Dist: rich>=14.0.0
Provides-Extra: cli
Requires-Dist: rich>=13.7.0; extra == 'cli'
Provides-Extra: dev
Requires-Dist: mypy>=1.10.0; extra == 'dev'
Requires-Dist: pytest-cov>=5.0.0; extra == 'dev'
Requires-Dist: pytest>=8.2.0; extra == 'dev'
Requires-Dist: ruff>=0.4.0; extra == 'dev'
